[
  {
    "seedKey": "transaction-contribution-member-group-02-0001-2026-01",
    "_id": "29cf114eea48163d8d31979b",
    "userId": "1532069100f8d7125b649466",
    "reference": "GC-798a2edec7542a02f62747c6",
    "amount": 10000,
    "type": "group_contribution",
    "status": "success",
    "description": "Group contribution - Golden Champions",
    "channel": "seed",
    "groupId": "f13266e9a87019f9d50f8c6c",
    "groupName": "Golden Champions",
    "metadata": {
      "contributionId": "798a2edec7542a02f62747c6",
      "month": 1,
      "year": 2026,
      "contributionType": "revolving"
    },
    "gateway": "internal",
    "date": "2026-01-05T00:00:00.000Z",
    "updatedAt": "2026-01-05T00:00:00.000Z"
  },
  {
    "seedKey": "transaction-contribution-member-group-02-0001-2026-02",
    "_id": "e4ed1de1d04d332dc7732559",
    "userId": "1532069100f8d7125b649466",
    "reference": "GC-f41bcecf08f01e32eb4516aa",
    "amount": 5000,
    "type": "group_contribution",
    "status": "success",
    "description": "Group contribution - Golden Champions",
    "channel": "seed",
    "groupId": "f13266e9a87019f9d50f8c6c",
    "groupName": "Golden Champions",
    "metadata": {
      "contributionId": "f41bcecf08f01e32eb4516aa",
      "month": 2,
      "year": 2026,
      "contributionType": "revolving"
    },
    "gateway": "internal",
    "date": "2026-02-05T00:00:00.000Z",
    "updatedAt": "2026-02-05T00:00:00.000Z"
  },
  {
    "seedKey": "transaction-contribution-member-group-02-0002-2026-01",
    "_id": "690ae0b3907aec7ba487f47c",
    "userId": "c895262779361acecee3f8ea",
    "reference": "GC-6e0083a31603fcd385c1c4ac",
    "amount": 10000,
    "type": "group_contribution",
    "status": "success",
    "description": "Group contribution - Golden Champions",
    "channel": "seed",
    "groupId": "f13266e9a87019f9d50f8c6c",
    "groupName": "Golden Champions",
    "metadata": {
      "contributionId": "6e0083a31603fcd385c1c4ac",
      "month": 1,
      "year": 2026,
      "contributionType": "revolving"
    },
    "gateway": "internal",
    "date": "2026-01-05T00:00:00.000Z",
    "updatedAt": "2026-01-05T00:00:00.000Z"
  },
  {
    "seedKey": "transaction-contribution-member-group-02-0002-2026-02",
    "_id": "e99eebb4cb619429fc6a47b8",
    "userId": "c895262779361acecee3f8ea",
    "reference": "GC-2a63dba962c9c0f5461f3f84",
    "amount": 5000,
    "type": "group_contribution",
    "status": "success",
    "description": "Group contribution - Golden Champions",
    "channel": "seed",
    "groupId": "f13266e9a87019f9d50f8c6c",
    "groupName": "Golden Champions",
    "metadata": {
      "contributionId": "2a63dba962c9c0f5461f3f84",
      "month": 2,
      "year": 2026,
      "contributionType": "revolving"
    },
    "gateway": "internal",
    "date": "2026-02-05T00:00:00.000Z",
    "updatedAt": "2026-02-05T00:00:00.000Z"
  },
  {
    "seedKey": "transaction-contribution-member-group-02-0003-2026-01",
    "_id": "47f81ecfc8530a5cb101544d",
    "userId": "16a48722777ed70b5084a6d7",
    "reference": "GC-32d62f8f110bacf9d5ca60b4",
    "amount": 10000,
    "type": "group_contribution",
    "status": "success",
    "description": "Group contribution - Golden Champions",
    "channel": "seed",
    "groupId": "f13266e9a87019f9d50f8c6c",
    "groupName": "Golden Champions",
    "metadata": {
      "contributionId": "32d62f8f110bacf9d5ca60b4",
      "month": 1,
      "year": 2026,
      "contributionType": "revolving"
    },
    "gateway": "internal",
    "date": "2026-01-05T00:00:00.000Z",
    "updatedAt": "2026-01-05T00:00:00.000Z"
  },
  {
    "seedKey": "transaction-contribution-member-group-02-0003-2026-02",
    "_id": "37b577e2c79628da49e10b00",
    "userId": "16a48722777ed70b5084a6d7",
    "reference": "GC-a164ec74bc37e14e827971be",
    "amount": 5000,
    "type": "group_contribution",
    "status": "success",
    "description": "Group contribution - Golden Champions",
    "channel": "seed",
    "groupId": "f13266e9a87019f9d50f8c6c",
    "groupName": "Golden Champions",
    "metadata": {
      "contributionId": "a164ec74bc37e14e827971be",
      "month": 2,
      "year": 2026,
      "contributionType": "revolving"
    },
    "gateway": "internal",
    "date": "2026-02-05T00:00:00.000Z",
    "updatedAt": "2026-02-05T00:00:00.000Z"
  },
  {
    "seedKey": "transaction-contribution-member-group-02-0004-2026-01",
    "_id": "23b5df52b91a814545165777",
    "userId": "3b6aa834731876b24711a14e",
    "reference": "GC-9f3301d5e8310d8c74f0f19b",
    "amount": 10000,
    "type": "group_contribution",
    "status": "success",
    "description": "Group contribution - Golden Champions",
    "channel": "seed",
    "groupId": "f13266e9a87019f9d50f8c6c",
    "groupName": "Golden Champions",
    "metadata": {
      "contributionId": "9f3301d5e8310d8c74f0f19b",
      "month": 1,
      "year": 2026,
      "contributionType": "revolving"
    },
    "gateway": "internal",
    "date": "2026-01-05T00:00:00.000Z",
    "updatedAt": "2026-01-05T00:00:00.000Z"
  },
  {
    "seedKey": "transaction-contribution-member-group-02-0004-2026-02",
    "_id": "4626675da2cedf5f75019374",
    "userId": "3b6aa834731876b24711a14e",
    "reference": "GC-21a0b1afc785deedb6fdd214",
    "amount": 5000,
    "type": "group_contribution",
    "status": "success",
    "description": "Group contribution - Golden Champions",
    "channel": "seed",
    "groupId": "f13266e9a87019f9d50f8c6c",
    "groupName": "Golden Champions",
    "metadata": {
      "contributionId": "21a0b1afc785deedb6fdd214",
      "month": 2,
      "year": 2026,
      "contributionType": "revolving"
    },
    "gateway": "internal",
    "date": "2026-02-05T00:00:00.000Z",
    "updatedAt": "2026-02-05T00:00:00.000Z"
  },
  {
    "seedKey": "transaction-contribution-member-group-02-0005-2026-01",
    "_id": "b323b11eb4b20c6ff7c03e62",
    "userId": "15b270e37381b76fb9879d58",
    "reference": "GC-44d1d85dc30e9d178f91fbbe",
    "amount": 20000,
    "type": "group_contribution",
    "status": "success",
    "description": "Group contribution - Golden Champions",
    "channel": "seed",
    "groupId": "f13266e9a87019f9d50f8c6c",
    "groupName": "Golden Champions",
    "metadata": {
      "contributionId": "44d1d85dc30e9d178f91fbbe",
      "month": 1,
      "year": 2026,
      "contributionType": "revolving"
    },
    "gateway": "internal",
    "date": "2026-01-05T00:00:00.000Z",
    "updatedAt": "2026-01-05T00:00:00.000Z"
  },
  {
    "seedKey": "transaction-contribution-member-group-02-0005-2026-02",
    "_id": "69626c36cefc34686adb51b5",
    "userId": "15b270e37381b76fb9879d58",
    "reference": "GC-9ec54fa2afc03560db12e083",
    "amount": 10000,
    "type": "group_contribution",
    "status": "success",
    "description": "Group contribution - Golden Champions",
    "channel": "seed",
    "groupId": "f13266e9a87019f9d50f8c6c",
    "groupName": "Golden Champions",
    "metadata": {
      "contributionId": "9ec54fa2afc03560db12e083",
      "month": 2,
      "year": 2026,
      "contributionType": "revolving"
    },
    "gateway": "internal",
    "date": "2026-02-05T00:00:00.000Z",
    "updatedAt": "2026-02-05T00:00:00.000Z"
  },
  {
    "seedKey": "transaction-contribution-member-group-02-0006-2026-01",
    "_id": "99b3369b17c78028495eeee2",
    "userId": "0b13e6587d11f3aea907b961",
    "reference": "GC-56e1d01b3171a84a1a941dc2",
    "amount": 20000,
    "type": "group_contribution",
    "status": "success",
    "description": "Group contribution - Golden Champions",
    "channel": "seed",
    "groupId": "f13266e9a87019f9d50f8c6c",
    "groupName": "Golden Champions",
    "metadata": {
      "contributionId": "56e1d01b3171a84a1a941dc2",
      "month": 1,
      "year": 2026,
      "contributionType": "revolving"
    },
    "gateway": "internal",
    "date": "2026-01-05T00:00:00.000Z",
    "updatedAt": "2026-01-05T00:00:00.000Z"
  },
  {
    "seedKey": "transaction-contribution-member-group-02-0006-2026-02",
    "_id": "7c8979664b86d6834a57eb32",
    "userId": "0b13e6587d11f3aea907b961",
    "reference": "GC-e08e205a70ea7d5aad86b1fe",
    "amount": 20000,
    "type": "group_contribution",
    "status": "success",
    "description": "Group contribution - Golden Champions",
    "channel": "seed",
    "groupId": "f13266e9a87019f9d50f8c6c",
    "groupName": "Golden Champions",
    "metadata": {
      "contributionId": "e08e205a70ea7d5aad86b1fe",
      "month": 2,
      "year": 2026,
      "contributionType": "revolving"
    },
    "gateway": "internal",
    "date": "2026-02-05T00:00:00.000Z",
    "updatedAt": "2026-02-05T00:00:00.000Z"
  },
  {
    "seedKey": "transaction-contribution-member-group-02-0007-2026-01",
    "_id": "ddb41dffc2d613d83623b943",
    "userId": "aff1c9290504fd4e25f33c14",
    "reference": "GC-bf77b43dfcc4cc77046effa6",
    "amount": 10000,
    "type": "group_contribution",
    "status": "success",
    "description": "Group contribution - Golden Champions",
    "channel": "seed",
    "groupId": "f13266e9a87019f9d50f8c6c",
    "groupName": "Golden Champions",
    "metadata": {
      "contributionId": "bf77b43dfcc4cc77046effa6",
      "month": 1,
      "year": 2026,
      "contributionType": "revolving"
    },
    "gateway": "internal",
    "date": "2026-01-05T00:00:00.000Z",
    "updatedAt": "2026-01-05T00:00:00.000Z"
  },
  {
    "seedKey": "transaction-contribution-member-group-02-0007-2026-02",
    "_id": "131fda305ca7b4a4f61873a0",
    "userId": "aff1c9290504fd4e25f33c14",
    "reference": "GC-e60aff5f8ceddb124f52ef20",
    "amount": 10000,
    "type": "group_contribution",
    "status": "success",
    "description": "Group contribution - Golden Champions",
    "channel": "seed",
    "groupId": "f13266e9a87019f9d50f8c6c",
    "groupName": "Golden Champions",
    "metadata": {
      "contributionId": "e60aff5f8ceddb124f52ef20",
      "month": 2,
      "year": 2026,
      "contributionType": "revolving"
    },
    "gateway": "internal",
    "date": "2026-02-05T00:00:00.000Z",
    "updatedAt": "2026-02-05T00:00:00.000Z"
  },
  {
    "seedKey": "transaction-contribution-member-group-02-0008-2026-01",
    "_id": "4a8170e78cb8a236977cd65c",
    "userId": "f550a75e21ccaf13d3f31a8d",
    "reference": "GC-258f92461ced055e60e51ddc",
    "amount": 20000,
    "type": "group_contribution",
    "status": "success",
    "description": "Group contribution - Golden Champions",
    "channel": "seed",
    "groupId": "f13266e9a87019f9d50f8c6c",
    "groupName": "Golden Champions",
    "metadata": {
      "contributionId": "258f92461ced055e60e51ddc",
      "month": 1,
      "year": 2026,
      "contributionType": "revolving"
    },
    "gateway": "internal",
    "date": "2026-01-05T00:00:00.000Z",
    "updatedAt": "2026-01-05T00:00:00.000Z"
  },
  {
    "seedKey": "transaction-contribution-member-group-02-0008-2026-02",
    "_id": "947503e96cb5dd152f0babdb",
    "userId": "f550a75e21ccaf13d3f31a8d",
    "reference": "GC-4fe7d73682c846860b6d5633",
    "amount": 10000,
    "type": "group_contribution",
    "status": "success",
    "description": "Group contribution - Golden Champions",
    "channel": "seed",
    "groupId": "f13266e9a87019f9d50f8c6c",
    "groupName": "Golden Champions",
    "metadata": {
      "contributionId": "4fe7d73682c846860b6d5633",
      "month": 2,
      "year": 2026,
      "contributionType": "revolving"
    },
    "gateway": "internal",
    "date": "2026-02-05T00:00:00.000Z",
    "updatedAt": "2026-02-05T00:00:00.000Z"
  },
  {
    "seedKey": "transaction-contribution-member-group-02-0009-2026-01",
    "_id": "73a20fcc5e863b3e9b3aac60",
    "userId": "5d259e4030759a068424b36d",
    "reference": "GC-976cd252ec5579b1a2e5f46c",
    "amount": 20000,
    "type": "group_contribution",
    "status": "success",
    "description": "Group contribution - Golden Champions",
    "channel": "seed",
    "groupId": "f13266e9a87019f9d50f8c6c",
    "groupName": "Golden Champions",
    "metadata": {
      "contributionId": "976cd252ec5579b1a2e5f46c",
      "month": 1,
      "year": 2026,
      "contributionType": "revolving"
    },
    "gateway": "internal",
    "date": "2026-01-05T00:00:00.000Z",
    "updatedAt": "2026-01-05T00:00:00.000Z"
  },
  {
    "seedKey": "transaction-contribution-member-group-02-0009-2026-02",
    "_id": "3b5f7892965187b0d13d3713",
    "userId": "5d259e4030759a068424b36d",
    "reference": "GC-84331f7cc90b2eb768aab3c0",
    "amount": 15000,
    "type": "group_contribution",
    "status": "success",
    "description": "Group contribution - Golden Champions",
    "channel": "seed",
    "groupId": "f13266e9a87019f9d50f8c6c",
    "groupName": "Golden Champions",
    "metadata": {
      "contributionId": "84331f7cc90b2eb768aab3c0",
      "month": 2,
      "year": 2026,
      "contributionType": "revolving"
    },
    "gateway": "internal",
    "date": "2026-02-05T00:00:00.000Z",
    "updatedAt": "2026-02-05T00:00:00.000Z"
  },
  {
    "seedKey": "transaction-contribution-member-group-02-0010-2026-01",
    "_id": "e9b241e50abfc7d1a5786ea6",
    "userId": "bfcbef66d307e3cb49b8677c",
    "reference": "GC-daa37dec2b17a096525eef86",
    "amount": 20000,
    "type": "group_contribution",
    "status": "success",
    "description": "Group contribution - Golden Champions",
    "channel": "seed",
    "groupId": "f13266e9a87019f9d50f8c6c",
    "groupName": "Golden Champions",
    "metadata": {
      "contributionId": "daa37dec2b17a096525eef86",
      "month": 1,
      "year": 2026,
      "contributionType": "revolving"
    },
    "gateway": "internal",
    "date": "2026-01-05T00:00:00.000Z",
    "updatedAt": "2026-01-05T00:00:00.000Z"
  },
  {
    "seedKey": "transaction-contribution-member-group-02-0010-2026-02",
    "_id": "fe5702d154052fb407bb972f",
    "userId": "bfcbef66d307e3cb49b8677c",
    "reference": "GC-0be969a75eb0582f2288a7e1",
    "amount": 20000,
    "type": "group_contribution",
    "status": "success",
    "description": "Group contribution - Golden Champions",
    "channel": "seed",
    "groupId": "f13266e9a87019f9d50f8c6c",
    "groupName": "Golden Champions",
    "metadata": {
      "contributionId": "0be969a75eb0582f2288a7e1",
      "month": 2,
      "year": 2026,
      "contributionType": "revolving"
    },
    "gateway": "internal",
    "date": "2026-02-05T00:00:00.000Z",
    "updatedAt": "2026-02-05T00:00:00.000Z"
  },
  {
    "seedKey": "transaction-contribution-member-group-02-0011-2026-01",
    "_id": "091e418c7324fb29ca0f99a3",
    "userId": "1226dd284fa4ad2610c4f668",
    "reference": "GC-91ae40e131f67b4cc6792d23",
    "amount": 20000,
    "type": "group_contribution",
    "status": "success",
    "description": "Group contribution - Golden Champions",
    "channel": "seed",
    "groupId": "f13266e9a87019f9d50f8c6c",
    "groupName": "Golden Champions",
    "metadata": {
      "contributionId": "91ae40e131f67b4cc6792d23",
      "month": 1,
      "year": 2026,
      "contributionType": "revolving"
    },
    "gateway": "internal",
    "date": "2026-01-05T00:00:00.000Z",
    "updatedAt": "2026-01-05T00:00:00.000Z"
  },
  {
    "seedKey": "transaction-contribution-member-group-02-0011-2026-02",
    "_id": "28771b3a2b73d450bae8d0fb",
    "userId": "1226dd284fa4ad2610c4f668",
    "reference": "GC-ccd12ce9fbe98d6f8d438a76",
    "amount": 10000,
    "type": "group_contribution",
    "status": "success",
    "description": "Group contribution - Golden Champions",
    "channel": "seed",
    "groupId": "f13266e9a87019f9d50f8c6c",
    "groupName": "Golden Champions",
    "metadata": {
      "contributionId": "ccd12ce9fbe98d6f8d438a76",
      "month": 2,
      "year": 2026,
      "contributionType": "revolving"
    },
    "gateway": "internal",
    "date": "2026-02-05T00:00:00.000Z",
    "updatedAt": "2026-02-05T00:00:00.000Z"
  },
  {
    "seedKey": "transaction-contribution-member-group-02-0012-2026-01",
    "_id": "5c65b9d5bad8a1ced3422355",
    "userId": "e940be9f5281c275aa6cb30b",
    "reference": "GC-a5adffe75b39d1407adc4aa1",
    "amount": 30000,
    "type": "group_contribution",
    "status": "success",
    "description": "Group contribution - Golden Champions",
    "channel": "seed",
    "groupId": "f13266e9a87019f9d50f8c6c",
    "groupName": "Golden Champions",
    "metadata": {
      "contributionId": "a5adffe75b39d1407adc4aa1",
      "month": 1,
      "year": 2026,
      "contributionType": "revolving"
    },
    "gateway": "internal",
    "date": "2026-01-05T00:00:00.000Z",
    "updatedAt": "2026-01-05T00:00:00.000Z"
  },
  {
    "seedKey": "transaction-contribution-member-group-02-0012-2026-02",
    "_id": "815738999b95d73474f564ad",
    "userId": "e940be9f5281c275aa6cb30b",
    "reference": "GC-1ee80613b030af1a4c7ea3ae",
    "amount": 15000,
    "type": "group_contribution",
    "status": "success",
    "description": "Group contribution - Golden Champions",
    "channel": "seed",
    "groupId": "f13266e9a87019f9d50f8c6c",
    "groupName": "Golden Champions",
    "metadata": {
      "contributionId": "1ee80613b030af1a4c7ea3ae",
      "month": 2,
      "year": 2026,
      "contributionType": "revolving"
    },
    "gateway": "internal",
    "date": "2026-02-05T00:00:00.000Z",
    "updatedAt": "2026-02-05T00:00:00.000Z"
  },
  {
    "seedKey": "transaction-contribution-member-group-02-0013-2026-01",
    "_id": "a31ebc61102b6dca78de1fcd",
    "userId": "6a669258e28d0e5b2a97019b",
    "reference": "GC-314e51edcff228fdc2846d82",
    "amount": 30000,
    "type": "group_contribution",
    "status": "success",
    "description": "Group contribution - Golden Champions",
    "channel": "seed",
    "groupId": "f13266e9a87019f9d50f8c6c",
    "groupName": "Golden Champions",
    "metadata": {
      "contributionId": "314e51edcff228fdc2846d82",
      "month": 1,
      "year": 2026,
      "contributionType": "revolving"
    },
    "gateway": "internal",
    "date": "2026-01-05T00:00:00.000Z",
    "updatedAt": "2026-01-05T00:00:00.000Z"
  },
  {
    "seedKey": "transaction-contribution-member-group-02-0013-2026-02",
    "_id": "a59f615043faff05b74d2c8b",
    "userId": "6a669258e28d0e5b2a97019b",
    "reference": "GC-fa394259a0745465b97b2764",
    "amount": 15000,
    "type": "group_contribution",
    "status": "success",
    "description": "Group contribution - Golden Champions",
    "channel": "seed",
    "groupId": "f13266e9a87019f9d50f8c6c",
    "groupName": "Golden Champions",
    "metadata": {
      "contributionId": "fa394259a0745465b97b2764",
      "month": 2,
      "year": 2026,
      "contributionType": "revolving"
    },
    "gateway": "internal",
    "date": "2026-02-05T00:00:00.000Z",
    "updatedAt": "2026-02-05T00:00:00.000Z"
  },
  {
    "seedKey": "transaction-contribution-member-group-02-0014-2026-01",
    "_id": "ca85ad7d7a39433236ee7d80",
    "userId": "1b2e938e037f0c32b5f07321",
    "reference": "GC-64e377382192bc75c02a5804",
    "amount": 30000,
    "type": "group_contribution",
    "status": "success",
    "description": "Group contribution - Golden Champions",
    "channel": "seed",
    "groupId": "f13266e9a87019f9d50f8c6c",
    "groupName": "Golden Champions",
    "metadata": {
      "contributionId": "64e377382192bc75c02a5804",
      "month": 1,
      "year": 2026,
      "contributionType": "revolving"
    },
    "gateway": "internal",
    "date": "2026-01-05T00:00:00.000Z",
    "updatedAt": "2026-01-05T00:00:00.000Z"
  },
  {
    "seedKey": "transaction-contribution-member-group-02-0014-2026-02",
    "_id": "2dded415c6145359abadd9db",
    "userId": "1b2e938e037f0c32b5f07321",
    "reference": "GC-c2b57026ed283434cc375c50",
    "amount": 15000,
    "type": "group_contribution",
    "status": "success",
    "description": "Group contribution - Golden Champions",
    "channel": "seed",
    "groupId": "f13266e9a87019f9d50f8c6c",
    "groupName": "Golden Champions",
    "metadata": {
      "contributionId": "c2b57026ed283434cc375c50",
      "month": 2,
      "year": 2026,
      "contributionType": "revolving"
    },
    "gateway": "internal",
    "date": "2026-02-05T00:00:00.000Z",
    "updatedAt": "2026-02-05T00:00:00.000Z"
  },
  {
    "seedKey": "transaction-contribution-member-group-02-0015-2026-01",
    "_id": "10fd08fbc4025104d95036e9",
    "userId": "799409fb0f25d7aba8a34108",
    "reference": "GC-a0f26734b17833ef86aa3e83",
    "amount": 30000,
    "type": "group_contribution",
    "status": "success",
    "description": "Group contribution - Golden Champions",
    "channel": "seed",
    "groupId": "f13266e9a87019f9d50f8c6c",
    "groupName": "Golden Champions",
    "metadata": {
      "contributionId": "a0f26734b17833ef86aa3e83",
      "month": 1,
      "year": 2026,
      "contributionType": "revolving"
    },
    "gateway": "internal",
    "date": "2026-01-05T00:00:00.000Z",
    "updatedAt": "2026-01-05T00:00:00.000Z"
  },
  {
    "seedKey": "transaction-contribution-member-group-02-0015-2026-02",
    "_id": "e43760165b9f4f5cf462c4f0",
    "userId": "799409fb0f25d7aba8a34108",
    "reference": "GC-88bffacbf45f209dbd492501",
    "amount": 15000,
    "type": "group_contribution",
    "status": "success",
    "description": "Group contribution - Golden Champions",
    "channel": "seed",
    "groupId": "f13266e9a87019f9d50f8c6c",
    "groupName": "Golden Champions",
    "metadata": {
      "contributionId": "88bffacbf45f209dbd492501",
      "month": 2,
      "year": 2026,
      "contributionType": "revolving"
    },
    "gateway": "internal",
    "date": "2026-02-05T00:00:00.000Z",
    "updatedAt": "2026-02-05T00:00:00.000Z"
  },
  {
    "seedKey": "transaction-contribution-member-group-02-0016-2026-01",
    "_id": "3de330ed40a31115e2255090",
    "userId": "b906c653d9513ea6603639af",
    "reference": "GC-fd25a727e0e4b0b8863c0907",
    "amount": 30000,
    "type": "group_contribution",
    "status": "success",
    "description": "Group contribution - Golden Champions",
    "channel": "seed",
    "groupId": "f13266e9a87019f9d50f8c6c",
    "groupName": "Golden Champions",
    "metadata": {
      "contributionId": "fd25a727e0e4b0b8863c0907",
      "month": 1,
      "year": 2026,
      "contributionType": "revolving"
    },
    "gateway": "internal",
    "date": "2026-01-05T00:00:00.000Z",
    "updatedAt": "2026-01-05T00:00:00.000Z"
  },
  {
    "seedKey": "transaction-contribution-member-group-02-0016-2026-02",
    "_id": "df369bc244b48f3a0be4cd5d",
    "userId": "b906c653d9513ea6603639af",
    "reference": "GC-30ba683c0949b4ee569d9dbe",
    "amount": 15000,
    "type": "group_contribution",
    "status": "success",
    "description": "Group contribution - Golden Champions",
    "channel": "seed",
    "groupId": "f13266e9a87019f9d50f8c6c",
    "groupName": "Golden Champions",
    "metadata": {
      "contributionId": "30ba683c0949b4ee569d9dbe",
      "month": 2,
      "year": 2026,
      "contributionType": "revolving"
    },
    "gateway": "internal",
    "date": "2026-02-05T00:00:00.000Z",
    "updatedAt": "2026-02-05T00:00:00.000Z"
  },
  {
    "seedKey": "transaction-contribution-member-group-02-0017-2026-01",
    "_id": "d36753a4fc7f425117201122",
    "userId": "37aff28c8bcee1d00b2632db",
    "reference": "GC-7b915366c545ff35e3ec9c3f",
    "amount": 30000,
    "type": "group_contribution",
    "status": "success",
    "description": "Group contribution - Golden Champions",
    "channel": "seed",
    "groupId": "f13266e9a87019f9d50f8c6c",
    "groupName": "Golden Champions",
    "metadata": {
      "contributionId": "7b915366c545ff35e3ec9c3f",
      "month": 1,
      "year": 2026,
      "contributionType": "revolving"
    },
    "gateway": "internal",
    "date": "2026-01-05T00:00:00.000Z",
    "updatedAt": "2026-01-05T00:00:00.000Z"
  },
  {
    "seedKey": "transaction-contribution-member-group-02-0017-2026-02",
    "_id": "49bebf472695f2935eb81ce5",
    "userId": "37aff28c8bcee1d00b2632db",
    "reference": "GC-0b58039f522d1460b2bd9c45",
    "amount": 15000,
    "type": "group_contribution",
    "status": "success",
    "description": "Group contribution - Golden Champions",
    "channel": "seed",
    "groupId": "f13266e9a87019f9d50f8c6c",
    "groupName": "Golden Champions",
    "metadata": {
      "contributionId": "0b58039f522d1460b2bd9c45",
      "month": 2,
      "year": 2026,
      "contributionType": "revolving"
    },
    "gateway": "internal",
    "date": "2026-02-05T00:00:00.000Z",
    "updatedAt": "2026-02-05T00:00:00.000Z"
  },
  {
    "seedKey": "transaction-contribution-member-group-02-0018-2026-01",
    "_id": "64cbe1884607bc9853a27312",
    "userId": "0774e98de1120741f105d75a",
    "reference": "GC-62ab8f98cb461e3fb7a380c9",
    "amount": 30000,
    "type": "group_contribution",
    "status": "success",
    "description": "Group contribution - Golden Champions",
    "channel": "seed",
    "groupId": "f13266e9a87019f9d50f8c6c",
    "groupName": "Golden Champions",
    "metadata": {
      "contributionId": "62ab8f98cb461e3fb7a380c9",
      "month": 1,
      "year": 2026,
      "contributionType": "revolving"
    },
    "gateway": "internal",
    "date": "2026-01-05T00:00:00.000Z",
    "updatedAt": "2026-01-05T00:00:00.000Z"
  },
  {
    "seedKey": "transaction-contribution-member-group-02-0018-2026-02",
    "_id": "54e206cbe0f00a74e960ba27",
    "userId": "0774e98de1120741f105d75a",
    "reference": "GC-11abe241728fe479e0969dd5",
    "amount": 15000,
    "type": "group_contribution",
    "status": "success",
    "description": "Group contribution - Golden Champions",
    "channel": "seed",
    "groupId": "f13266e9a87019f9d50f8c6c",
    "groupName": "Golden Champions",
    "metadata": {
      "contributionId": "11abe241728fe479e0969dd5",
      "month": 2,
      "year": 2026,
      "contributionType": "revolving"
    },
    "gateway": "internal",
    "date": "2026-02-05T00:00:00.000Z",
    "updatedAt": "2026-02-05T00:00:00.000Z"
  },
  {
    "seedKey": "transaction-contribution-member-group-02-0019-2026-01",
    "_id": "5adefb37dc8c24ff81c776f4",
    "userId": "f7f0d06eb46b1b1afb6bba6e",
    "reference": "GC-a5e148c5ea72c03c36e477f4",
    "amount": 40000,
    "type": "group_contribution",
    "status": "success",
    "description": "Group contribution - Golden Champions",
    "channel": "seed",
    "groupId": "f13266e9a87019f9d50f8c6c",
    "groupName": "Golden Champions",
    "metadata": {
      "contributionId": "a5e148c5ea72c03c36e477f4",
      "month": 1,
      "year": 2026,
      "contributionType": "revolving"
    },
    "gateway": "internal",
    "date": "2026-01-05T00:00:00.000Z",
    "updatedAt": "2026-01-05T00:00:00.000Z"
  },
  {
    "seedKey": "transaction-contribution-member-group-02-0019-2026-02",
    "_id": "f2bf6bb5c30f421e335ae8b7",
    "userId": "f7f0d06eb46b1b1afb6bba6e",
    "reference": "GC-b10022fe2873562356c4b980",
    "amount": 20000,
    "type": "group_contribution",
    "status": "success",
    "description": "Group contribution - Golden Champions",
    "channel": "seed",
    "groupId": "f13266e9a87019f9d50f8c6c",
    "groupName": "Golden Champions",
    "metadata": {
      "contributionId": "b10022fe2873562356c4b980",
      "month": 2,
      "year": 2026,
      "contributionType": "revolving"
    },
    "gateway": "internal",
    "date": "2026-02-05T00:00:00.000Z",
    "updatedAt": "2026-02-05T00:00:00.000Z"
  },
  {
    "seedKey": "transaction-contribution-member-group-02-0020-2026-01",
    "_id": "3c7ccd3c92124ed3d894d8a2",
    "userId": "cd167526fe2e8cfccde3026d",
    "reference": "GC-4f917cca176b34e7286145f1",
    "amount": 20000,
    "type": "group_contribution",
    "status": "success",
    "description": "Group contribution - Golden Champions",
    "channel": "seed",
    "groupId": "f13266e9a87019f9d50f8c6c",
    "groupName": "Golden Champions",
    "metadata": {
      "contributionId": "4f917cca176b34e7286145f1",
      "month": 1,
      "year": 2026,
      "contributionType": "revolving"
    },
    "gateway": "internal",
    "date": "2026-01-05T00:00:00.000Z",
    "updatedAt": "2026-01-05T00:00:00.000Z"
  },
  {
    "seedKey": "transaction-contribution-member-group-02-0021-2026-01",
    "_id": "90e01d4c8baa80f51db15ffb",
    "userId": "9fe1e211fc3684625214f549",
    "reference": "GC-89b3a49f0bcf1d1cb9986121",
    "amount": 40000,
    "type": "group_contribution",
    "status": "success",
    "description": "Group contribution - Golden Champions",
    "channel": "seed",
    "groupId": "f13266e9a87019f9d50f8c6c",
    "groupName": "Golden Champions",
    "metadata": {
      "contributionId": "89b3a49f0bcf1d1cb9986121",
      "month": 1,
      "year": 2026,
      "contributionType": "revolving"
    },
    "gateway": "internal",
    "date": "2026-01-05T00:00:00.000Z",
    "updatedAt": "2026-01-05T00:00:00.000Z"
  },
  {
    "seedKey": "transaction-contribution-member-group-02-0021-2026-02",
    "_id": "e22e25ffe18082d3a0338c5b",
    "userId": "9fe1e211fc3684625214f549",
    "reference": "GC-3f92f743432a2d38ce9e8d8e",
    "amount": 20000,
    "type": "group_contribution",
    "status": "success",
    "description": "Group contribution - Golden Champions",
    "channel": "seed",
    "groupId": "f13266e9a87019f9d50f8c6c",
    "groupName": "Golden Champions",
    "metadata": {
      "contributionId": "3f92f743432a2d38ce9e8d8e",
      "month": 2,
      "year": 2026,
      "contributionType": "revolving"
    },
    "gateway": "internal",
    "date": "2026-02-05T00:00:00.000Z",
    "updatedAt": "2026-02-05T00:00:00.000Z"
  },
  {
    "seedKey": "transaction-contribution-member-group-02-0022-2026-01",
    "_id": "961fdd1f6e2721f976805f96",
    "userId": "e854da8ed137065ceb4b76ea",
    "reference": "GC-7f85b0246eb4f8cd7d24c2bc",
    "amount": 40000,
    "type": "group_contribution",
    "status": "success",
    "description": "Group contribution - Golden Champions",
    "channel": "seed",
    "groupId": "f13266e9a87019f9d50f8c6c",
    "groupName": "Golden Champions",
    "metadata": {
      "contributionId": "7f85b0246eb4f8cd7d24c2bc",
      "month": 1,
      "year": 2026,
      "contributionType": "revolving"
    },
    "gateway": "internal",
    "date": "2026-01-05T00:00:00.000Z",
    "updatedAt": "2026-01-05T00:00:00.000Z"
  },
  {
    "seedKey": "transaction-contribution-member-group-02-0022-2026-02",
    "_id": "4e34f979260465f3f9c3c842",
    "userId": "e854da8ed137065ceb4b76ea",
    "reference": "GC-f3559510ac32f2657263dbd3",
    "amount": 20000,
    "type": "group_contribution",
    "status": "success",
    "description": "Group contribution - Golden Champions",
    "channel": "seed",
    "groupId": "f13266e9a87019f9d50f8c6c",
    "groupName": "Golden Champions",
    "metadata": {
      "contributionId": "f3559510ac32f2657263dbd3",
      "month": 2,
      "year": 2026,
      "contributionType": "revolving"
    },
    "gateway": "internal",
    "date": "2026-02-05T00:00:00.000Z",
    "updatedAt": "2026-02-05T00:00:00.000Z"
  },
  {
    "seedKey": "transaction-contribution-member-group-02-0023-2026-01",
    "_id": "b6097b377c6589bd0ee5b064",
    "userId": "7749b019c74d62355d3458f6",
    "reference": "GC-e8537c39cf5aabde61339f9b",
    "amount": 40000,
    "type": "group_contribution",
    "status": "success",
    "description": "Group contribution - Golden Champions",
    "channel": "seed",
    "groupId": "f13266e9a87019f9d50f8c6c",
    "groupName": "Golden Champions",
    "metadata": {
      "contributionId": "e8537c39cf5aabde61339f9b",
      "month": 1,
      "year": 2026,
      "contributionType": "revolving"
    },
    "gateway": "internal",
    "date": "2026-01-05T00:00:00.000Z",
    "updatedAt": "2026-01-05T00:00:00.000Z"
  },
  {
    "seedKey": "transaction-contribution-member-group-02-0023-2026-02",
    "_id": "16236791faffbb4812a84548",
    "userId": "7749b019c74d62355d3458f6",
    "reference": "GC-49b2fe085d04810631d46836",
    "amount": 20000,
    "type": "group_contribution",
    "status": "success",
    "description": "Group contribution - Golden Champions",
    "channel": "seed",
    "groupId": "f13266e9a87019f9d50f8c6c",
    "groupName": "Golden Champions",
    "metadata": {
      "contributionId": "49b2fe085d04810631d46836",
      "month": 2,
      "year": 2026,
      "contributionType": "revolving"
    },
    "gateway": "internal",
    "date": "2026-02-05T00:00:00.000Z",
    "updatedAt": "2026-02-05T00:00:00.000Z"
  },
  {
    "seedKey": "transaction-contribution-member-group-02-0024-2026-01",
    "_id": "55893ff72f2bef2fef82f3dc",
    "userId": "d260728ea126afd30c27db63",
    "reference": "GC-5d5778b38d353a15542e31ef",
    "amount": 20000,
    "type": "group_contribution",
    "status": "success",
    "description": "Group contribution - Golden Champions",
    "channel": "seed",
    "groupId": "f13266e9a87019f9d50f8c6c",
    "groupName": "Golden Champions",
    "metadata": {
      "contributionId": "5d5778b38d353a15542e31ef",
      "month": 1,
      "year": 2026,
      "contributionType": "revolving"
    },
    "gateway": "internal",
    "date": "2026-01-05T00:00:00.000Z",
    "updatedAt": "2026-01-05T00:00:00.000Z"
  },
  {
    "seedKey": "transaction-contribution-member-group-02-0025-2026-01",
    "_id": "339a55ed2299b3a0e851f2bd",
    "userId": "195e16d8157c01774be9c1f0",
    "reference": "GC-60d231551d2d8e6034225733",
    "amount": 40000,
    "type": "group_contribution",
    "status": "success",
    "description": "Group contribution - Golden Champions",
    "channel": "seed",
    "groupId": "f13266e9a87019f9d50f8c6c",
    "groupName": "Golden Champions",
    "metadata": {
      "contributionId": "60d231551d2d8e6034225733",
      "month": 1,
      "year": 2026,
      "contributionType": "revolving"
    },
    "gateway": "internal",
    "date": "2026-01-05T00:00:00.000Z",
    "updatedAt": "2026-01-05T00:00:00.000Z"
  },
  {
    "seedKey": "transaction-contribution-member-group-02-0025-2026-02",
    "_id": "e5ef582986917e6ea684a20d",
    "userId": "195e16d8157c01774be9c1f0",
    "reference": "GC-78b060d9df8e069f2a1b3d11",
    "amount": 20000,
    "type": "group_contribution",
    "status": "success",
    "description": "Group contribution - Golden Champions",
    "channel": "seed",
    "groupId": "f13266e9a87019f9d50f8c6c",
    "groupName": "Golden Champions",
    "metadata": {
      "contributionId": "78b060d9df8e069f2a1b3d11",
      "month": 2,
      "year": 2026,
      "contributionType": "revolving"
    },
    "gateway": "internal",
    "date": "2026-02-05T00:00:00.000Z",
    "updatedAt": "2026-02-05T00:00:00.000Z"
  },
  {
    "seedKey": "transaction-contribution-member-group-02-0026-2026-01",
    "_id": "a1f2273afb7be40aa9705e98",
    "userId": "89489a324007fbe0a8fcaba7",
    "reference": "GC-29ebd64aaf5e09959b573bb2",
    "amount": 50000,
    "type": "group_contribution",
    "status": "success",
    "description": "Group contribution - Golden Champions",
    "channel": "seed",
    "groupId": "f13266e9a87019f9d50f8c6c",
    "groupName": "Golden Champions",
    "metadata": {
      "contributionId": "29ebd64aaf5e09959b573bb2",
      "month": 1,
      "year": 2026,
      "contributionType": "revolving"
    },
    "gateway": "internal",
    "date": "2026-01-05T00:00:00.000Z",
    "updatedAt": "2026-01-05T00:00:00.000Z"
  },
  {
    "seedKey": "transaction-contribution-member-group-02-0026-2026-02",
    "_id": "7919b316962e050aa964fa1e",
    "userId": "89489a324007fbe0a8fcaba7",
    "reference": "GC-a466ee4ae38cee38419d12b0",
    "amount": 25000,
    "type": "group_contribution",
    "status": "success",
    "description": "Group contribution - Golden Champions",
    "channel": "seed",
    "groupId": "f13266e9a87019f9d50f8c6c",
    "groupName": "Golden Champions",
    "metadata": {
      "contributionId": "a466ee4ae38cee38419d12b0",
      "month": 2,
      "year": 2026,
      "contributionType": "revolving"
    },
    "gateway": "internal",
    "date": "2026-02-05T00:00:00.000Z",
    "updatedAt": "2026-02-05T00:00:00.000Z"
  },
  {
    "seedKey": "transaction-contribution-member-group-02-0027-2026-01",
    "_id": "f073fa14fa9bc5bca6e5bbe3",
    "userId": "b61f381f510ebe8cc983571f",
    "reference": "GC-c95d9b06c914538555144599",
    "amount": 50000,
    "type": "group_contribution",
    "status": "success",
    "description": "Group contribution - Golden Champions",
    "channel": "seed",
    "groupId": "f13266e9a87019f9d50f8c6c",
    "groupName": "Golden Champions",
    "metadata": {
      "contributionId": "c95d9b06c914538555144599",
      "month": 1,
      "year": 2026,
      "contributionType": "revolving"
    },
    "gateway": "internal",
    "date": "2026-01-05T00:00:00.000Z",
    "updatedAt": "2026-01-05T00:00:00.000Z"
  },
  {
    "seedKey": "transaction-contribution-member-group-02-0027-2026-02",
    "_id": "5ad93c33dbde0177c38ef6fd",
    "userId": "b61f381f510ebe8cc983571f",
    "reference": "GC-455f99800f7f8f0d47312c5b",
    "amount": 25000,
    "type": "group_contribution",
    "status": "success",
    "description": "Group contribution - Golden Champions",
    "channel": "seed",
    "groupId": "f13266e9a87019f9d50f8c6c",
    "groupName": "Golden Champions",
    "metadata": {
      "contributionId": "455f99800f7f8f0d47312c5b",
      "month": 2,
      "year": 2026,
      "contributionType": "revolving"
    },
    "gateway": "internal",
    "date": "2026-02-05T00:00:00.000Z",
    "updatedAt": "2026-02-05T00:00:00.000Z"
  },
  {
    "seedKey": "transaction-contribution-member-group-02-0028-2026-01",
    "_id": "9cf6de6ed36c071268a1bce7",
    "userId": "ace67f90a85c0fe13f8e033b",
    "reference": "GC-ebc9ade6e315d5118277d037",
    "amount": 50000,
    "type": "group_contribution",
    "status": "success",
    "description": "Group contribution - Golden Champions",
    "channel": "seed",
    "groupId": "f13266e9a87019f9d50f8c6c",
    "groupName": "Golden Champions",
    "metadata": {
      "contributionId": "ebc9ade6e315d5118277d037",
      "month": 1,
      "year": 2026,
      "contributionType": "revolving"
    },
    "gateway": "internal",
    "date": "2026-01-05T00:00:00.000Z",
    "updatedAt": "2026-01-05T00:00:00.000Z"
  },
  {
    "seedKey": "transaction-contribution-member-group-02-0028-2026-02",
    "_id": "397b468c86eb9fad9828c980",
    "userId": "ace67f90a85c0fe13f8e033b",
    "reference": "GC-17a639b971dd05db5c073e65",
    "amount": 25000,
    "type": "group_contribution",
    "status": "success",
    "description": "Group contribution - Golden Champions",
    "channel": "seed",
    "groupId": "f13266e9a87019f9d50f8c6c",
    "groupName": "Golden Champions",
    "metadata": {
      "contributionId": "17a639b971dd05db5c073e65",
      "month": 2,
      "year": 2026,
      "contributionType": "revolving"
    },
    "gateway": "internal",
    "date": "2026-02-05T00:00:00.000Z",
    "updatedAt": "2026-02-05T00:00:00.000Z"
  },
  {
    "seedKey": "transaction-contribution-member-group-02-0029-2026-01",
    "_id": "e824facbba4e040a3bc59f6b",
    "userId": "7e07c6feae3c13c1d57bddd5",
    "reference": "GC-3624660805d6c7ccdb046c2a",
    "amount": 50000,
    "type": "group_contribution",
    "status": "success",
    "description": "Group contribution - Golden Champions",
    "channel": "seed",
    "groupId": "f13266e9a87019f9d50f8c6c",
    "groupName": "Golden Champions",
    "metadata": {
      "contributionId": "3624660805d6c7ccdb046c2a",
      "month": 1,
      "year": 2026,
      "contributionType": "revolving"
    },
    "gateway": "internal",
    "date": "2026-01-05T00:00:00.000Z",
    "updatedAt": "2026-01-05T00:00:00.000Z"
  },
  {
    "seedKey": "transaction-contribution-member-group-02-0029-2026-02",
    "_id": "381ad9f3f4e60ad68569ff88",
    "userId": "7e07c6feae3c13c1d57bddd5",
    "reference": "GC-be3b431979e523063dcd6547",
    "amount": 25000,
    "type": "group_contribution",
    "status": "success",
    "description": "Group contribution - Golden Champions",
    "channel": "seed",
    "groupId": "f13266e9a87019f9d50f8c6c",
    "groupName": "Golden Champions",
    "metadata": {
      "contributionId": "be3b431979e523063dcd6547",
      "month": 2,
      "year": 2026,
      "contributionType": "revolving"
    },
    "gateway": "internal",
    "date": "2026-02-05T00:00:00.000Z",
    "updatedAt": "2026-02-05T00:00:00.000Z"
  },
  {
    "seedKey": "transaction-contribution-member-group-02-0030-2026-01",
    "_id": "c19da928346bd2602091eb7c",
    "userId": "22104ddc9344518969a085bc",
    "reference": "GC-19a0b0c7860c7a67d5df22fe",
    "amount": 50000,
    "type": "group_contribution",
    "status": "success",
    "description": "Group contribution - Golden Champions",
    "channel": "seed",
    "groupId": "f13266e9a87019f9d50f8c6c",
    "groupName": "Golden Champions",
    "metadata": {
      "contributionId": "19a0b0c7860c7a67d5df22fe",
      "month": 1,
      "year": 2026,
      "contributionType": "revolving"
    },
    "gateway": "internal",
    "date": "2026-01-05T00:00:00.000Z",
    "updatedAt": "2026-01-05T00:00:00.000Z"
  },
  {
    "seedKey": "transaction-contribution-member-group-02-0030-2026-02",
    "_id": "3dd201fce5172b95a98f231a",
    "userId": "22104ddc9344518969a085bc",
    "reference": "GC-7bb9a529f1d7f6026f6b44cf",
    "amount": 30000,
    "type": "group_contribution",
    "status": "success",
    "description": "Group contribution - Golden Champions",
    "channel": "seed",
    "groupId": "f13266e9a87019f9d50f8c6c",
    "groupName": "Golden Champions",
    "metadata": {
      "contributionId": "7bb9a529f1d7f6026f6b44cf",
      "month": 2,
      "year": 2026,
      "contributionType": "revolving"
    },
    "gateway": "internal",
    "date": "2026-02-05T00:00:00.000Z",
    "updatedAt": "2026-02-05T00:00:00.000Z"
  },
  {
    "seedKey": "transaction-contribution-member-group-02-0031-2026-01",
    "_id": "b73937185e51643292700dcc",
    "userId": "c1100a1ab35601cc51859548",
    "reference": "GC-a854d6b95a3584b782ef15e0",
    "amount": 50000,
    "type": "group_contribution",
    "status": "success",
    "description": "Group contribution - Golden Champions",
    "channel": "seed",
    "groupId": "f13266e9a87019f9d50f8c6c",
    "groupName": "Golden Champions",
    "metadata": {
      "contributionId": "a854d6b95a3584b782ef15e0",
      "month": 1,
      "year": 2026,
      "contributionType": "revolving"
    },
    "gateway": "internal",
    "date": "2026-01-05T00:00:00.000Z",
    "updatedAt": "2026-01-05T00:00:00.000Z"
  },
  {
    "seedKey": "transaction-contribution-member-group-02-0031-2026-02",
    "_id": "00b8e8bfbc0a4281a0e98c5e",
    "userId": "c1100a1ab35601cc51859548",
    "reference": "GC-b37be1ae1746f287e0c0d3db",
    "amount": 25000,
    "type": "group_contribution",
    "status": "success",
    "description": "Group contribution - Golden Champions",
    "channel": "seed",
    "groupId": "f13266e9a87019f9d50f8c6c",
    "groupName": "Golden Champions",
    "metadata": {
      "contributionId": "b37be1ae1746f287e0c0d3db",
      "month": 2,
      "year": 2026,
      "contributionType": "revolving"
    },
    "gateway": "internal",
    "date": "2026-02-05T00:00:00.000Z",
    "updatedAt": "2026-02-05T00:00:00.000Z"
  },
  {
    "seedKey": "transaction-contribution-member-group-02-0032-2026-01",
    "_id": "8601c290c0ce08be342a54b7",
    "userId": "a7e11f8c06b58c916967da8b",
    "reference": "GC-721d56c97900c4c1f2dc3f93",
    "amount": 60000,
    "type": "group_contribution",
    "status": "success",
    "description": "Group contribution - Golden Champions",
    "channel": "seed",
    "groupId": "f13266e9a87019f9d50f8c6c",
    "groupName": "Golden Champions",
    "metadata": {
      "contributionId": "721d56c97900c4c1f2dc3f93",
      "month": 1,
      "year": 2026,
      "contributionType": "revolving"
    },
    "gateway": "internal",
    "date": "2026-01-05T00:00:00.000Z",
    "updatedAt": "2026-01-05T00:00:00.000Z"
  },
  {
    "seedKey": "transaction-contribution-member-group-02-0032-2026-02",
    "_id": "49acd5ad9e5ef6b79dbf26a3",
    "userId": "a7e11f8c06b58c916967da8b",
    "reference": "GC-07db87f2dc5e9558518769b4",
    "amount": 30000,
    "type": "group_contribution",
    "status": "success",
    "description": "Group contribution - Golden Champions",
    "channel": "seed",
    "groupId": "f13266e9a87019f9d50f8c6c",
    "groupName": "Golden Champions",
    "metadata": {
      "contributionId": "07db87f2dc5e9558518769b4",
      "month": 2,
      "year": 2026,
      "contributionType": "revolving"
    },
    "gateway": "internal",
    "date": "2026-02-05T00:00:00.000Z",
    "updatedAt": "2026-02-05T00:00:00.000Z"
  },
  {
    "seedKey": "transaction-contribution-member-group-02-0033-2026-01",
    "_id": "554e3669c5b33187e994df76",
    "userId": "edfe921c2e7c277a66e92ac3",
    "reference": "GC-914f47fdff125cab33733957",
    "amount": 60000,
    "type": "group_contribution",
    "status": "success",
    "description": "Group contribution - Golden Champions",
    "channel": "seed",
    "groupId": "f13266e9a87019f9d50f8c6c",
    "groupName": "Golden Champions",
    "metadata": {
      "contributionId": "914f47fdff125cab33733957",
      "month": 1,
      "year": 2026,
      "contributionType": "revolving"
    },
    "gateway": "internal",
    "date": "2026-01-05T00:00:00.000Z",
    "updatedAt": "2026-01-05T00:00:00.000Z"
  },
  {
    "seedKey": "transaction-contribution-member-group-02-0033-2026-02",
    "_id": "b713dc91cdec26369b81b5e0",
    "userId": "edfe921c2e7c277a66e92ac3",
    "reference": "GC-74bd679f970b580b74078084",
    "amount": 30000,
    "type": "group_contribution",
    "status": "success",
    "description": "Group contribution - Golden Champions",
    "channel": "seed",
    "groupId": "f13266e9a87019f9d50f8c6c",
    "groupName": "Golden Champions",
    "metadata": {
      "contributionId": "74bd679f970b580b74078084",
      "month": 2,
      "year": 2026,
      "contributionType": "revolving"
    },
    "gateway": "internal",
    "date": "2026-02-05T00:00:00.000Z",
    "updatedAt": "2026-02-05T00:00:00.000Z"
  },
  {
    "seedKey": "transaction-contribution-member-group-02-0034-2026-01",
    "_id": "a1c73bcfb7132b073789bef6",
    "userId": "c3a049bb1d2b973ce99e14cf",
    "reference": "GC-ae23016d3dc1baa712791994",
    "amount": 60000,
    "type": "group_contribution",
    "status": "success",
    "description": "Group contribution - Golden Champions",
    "channel": "seed",
    "groupId": "f13266e9a87019f9d50f8c6c",
    "groupName": "Golden Champions",
    "metadata": {
      "contributionId": "ae23016d3dc1baa712791994",
      "month": 1,
      "year": 2026,
      "contributionType": "revolving"
    },
    "gateway": "internal",
    "date": "2026-01-05T00:00:00.000Z",
    "updatedAt": "2026-01-05T00:00:00.000Z"
  },
  {
    "seedKey": "transaction-contribution-member-group-02-0034-2026-02",
    "_id": "59895aec908606e7418dda2b",
    "userId": "c3a049bb1d2b973ce99e14cf",
    "reference": "GC-201a092e76ac4c2ad0fd7a5e",
    "amount": 30000,
    "type": "group_contribution",
    "status": "success",
    "description": "Group contribution - Golden Champions",
    "channel": "seed",
    "groupId": "f13266e9a87019f9d50f8c6c",
    "groupName": "Golden Champions",
    "metadata": {
      "contributionId": "201a092e76ac4c2ad0fd7a5e",
      "month": 2,
      "year": 2026,
      "contributionType": "revolving"
    },
    "gateway": "internal",
    "date": "2026-02-05T00:00:00.000Z",
    "updatedAt": "2026-02-05T00:00:00.000Z"
  },
  {
    "seedKey": "transaction-contribution-member-group-02-0035-2026-01",
    "_id": "f986aaac03ce22d8dd0a152b",
    "userId": "4c742c263b6d66070ea911e2",
    "reference": "GC-3ed913cdcf0554cc07d899f1",
    "amount": 30000,
    "type": "group_contribution",
    "status": "success",
    "description": "Group contribution - Golden Champions",
    "channel": "seed",
    "groupId": "f13266e9a87019f9d50f8c6c",
    "groupName": "Golden Champions",
    "metadata": {
      "contributionId": "3ed913cdcf0554cc07d899f1",
      "month": 1,
      "year": 2026,
      "contributionType": "revolving"
    },
    "gateway": "internal",
    "date": "2026-01-05T00:00:00.000Z",
    "updatedAt": "2026-01-05T00:00:00.000Z"
  },
  {
    "seedKey": "transaction-contribution-member-group-02-0036-2026-01",
    "_id": "03016a8827f9f2c287d8e96f",
    "userId": "029b457625d4400c8c1d5afe",
    "reference": "GC-df480cc496a44ca28b1643d8",
    "amount": 80000,
    "type": "group_contribution",
    "status": "success",
    "description": "Group contribution - Golden Champions",
    "channel": "seed",
    "groupId": "f13266e9a87019f9d50f8c6c",
    "groupName": "Golden Champions",
    "metadata": {
      "contributionId": "df480cc496a44ca28b1643d8",
      "month": 1,
      "year": 2026,
      "contributionType": "revolving"
    },
    "gateway": "internal",
    "date": "2026-01-05T00:00:00.000Z",
    "updatedAt": "2026-01-05T00:00:00.000Z"
  },
  {
    "seedKey": "transaction-contribution-member-group-02-0036-2026-02",
    "_id": "12c62cd7ea781eebd05f66e4",
    "userId": "029b457625d4400c8c1d5afe",
    "reference": "GC-9e9b4ff43103157d96351df6",
    "amount": 40000,
    "type": "group_contribution",
    "status": "success",
    "description": "Group contribution - Golden Champions",
    "channel": "seed",
    "groupId": "f13266e9a87019f9d50f8c6c",
    "groupName": "Golden Champions",
    "metadata": {
      "contributionId": "9e9b4ff43103157d96351df6",
      "month": 2,
      "year": 2026,
      "contributionType": "revolving"
    },
    "gateway": "internal",
    "date": "2026-02-05T00:00:00.000Z",
    "updatedAt": "2026-02-05T00:00:00.000Z"
  },
  {
    "seedKey": "transaction-contribution-member-group-02-0037-2026-01",
    "_id": "a710bf43906bbc6841b3d091",
    "userId": "288a24c3ff3e637c898a2184",
    "reference": "GC-ce7f572dc780e01beefd114f",
    "amount": 40000,
    "type": "group_contribution",
    "status": "success",
    "description": "Group contribution - Golden Champions",
    "channel": "seed",
    "groupId": "f13266e9a87019f9d50f8c6c",
    "groupName": "Golden Champions",
    "metadata": {
      "contributionId": "ce7f572dc780e01beefd114f",
      "month": 1,
      "year": 2026,
      "contributionType": "revolving"
    },
    "gateway": "internal",
    "date": "2026-01-05T00:00:00.000Z",
    "updatedAt": "2026-01-05T00:00:00.000Z"
  },
  {
    "seedKey": "transaction-contribution-member-group-02-0038-2026-01",
    "_id": "dd7a7f91276797a0a41cf5a0",
    "userId": "b44219bc45d9e46e1d24f961",
    "reference": "GC-90d076815d6ec66dc5a1ce8f",
    "amount": 80000,
    "type": "group_contribution",
    "status": "success",
    "description": "Group contribution - Golden Champions",
    "channel": "seed",
    "groupId": "f13266e9a87019f9d50f8c6c",
    "groupName": "Golden Champions",
    "metadata": {
      "contributionId": "90d076815d6ec66dc5a1ce8f",
      "month": 1,
      "year": 2026,
      "contributionType": "revolving"
    },
    "gateway": "internal",
    "date": "2026-01-05T00:00:00.000Z",
    "updatedAt": "2026-01-05T00:00:00.000Z"
  },
  {
    "seedKey": "transaction-contribution-member-group-02-0038-2026-02",
    "_id": "42b855fa8f6b5d6531da2b76",
    "userId": "b44219bc45d9e46e1d24f961",
    "reference": "GC-38c8d9dc6a605057e6ca4f11",
    "amount": 40000,
    "type": "group_contribution",
    "status": "success",
    "description": "Group contribution - Golden Champions",
    "channel": "seed",
    "groupId": "f13266e9a87019f9d50f8c6c",
    "groupName": "Golden Champions",
    "metadata": {
      "contributionId": "38c8d9dc6a605057e6ca4f11",
      "month": 2,
      "year": 2026,
      "contributionType": "revolving"
    },
    "gateway": "internal",
    "date": "2026-02-05T00:00:00.000Z",
    "updatedAt": "2026-02-05T00:00:00.000Z"
  },
  {
    "seedKey": "transaction-contribution-member-group-02-0039-2026-01",
    "_id": "60a9edc33bad6ddf281d26bf",
    "userId": "177bc5c9d2cfd4da69464bf4",
    "reference": "GC-bd8fbff23f7c1f0e98cf01b0",
    "amount": 80000,
    "type": "group_contribution",
    "status": "success",
    "description": "Group contribution - Golden Champions",
    "channel": "seed",
    "groupId": "f13266e9a87019f9d50f8c6c",
    "groupName": "Golden Champions",
    "metadata": {
      "contributionId": "bd8fbff23f7c1f0e98cf01b0",
      "month": 1,
      "year": 2026,
      "contributionType": "revolving"
    },
    "gateway": "internal",
    "date": "2026-01-05T00:00:00.000Z",
    "updatedAt": "2026-01-05T00:00:00.000Z"
  },
  {
    "seedKey": "transaction-contribution-member-group-02-0039-2026-02",
    "_id": "d9d7465882abc2b82cce219e",
    "userId": "177bc5c9d2cfd4da69464bf4",
    "reference": "GC-9c565c4545505d3c17fdfbfe",
    "amount": 40000,
    "type": "group_contribution",
    "status": "success",
    "description": "Group contribution - Golden Champions",
    "channel": "seed",
    "groupId": "f13266e9a87019f9d50f8c6c",
    "groupName": "Golden Champions",
    "metadata": {
      "contributionId": "9c565c4545505d3c17fdfbfe",
      "month": 2,
      "year": 2026,
      "contributionType": "revolving"
    },
    "gateway": "internal",
    "date": "2026-02-05T00:00:00.000Z",
    "updatedAt": "2026-02-05T00:00:00.000Z"
  },
  {
    "seedKey": "transaction-contribution-member-group-02-0040-2026-01",
    "_id": "e3e565af16d6f943965cd957",
    "userId": "a9bad8af8ad2ff655f788f37",
    "reference": "GC-8d696e77e6bb8d7cfeb5fbc6",
    "amount": 90000,
    "type": "group_contribution",
    "status": "success",
    "description": "Group contribution - Golden Champions",
    "channel": "seed",
    "groupId": "f13266e9a87019f9d50f8c6c",
    "groupName": "Golden Champions",
    "metadata": {
      "contributionId": "8d696e77e6bb8d7cfeb5fbc6",
      "month": 1,
      "year": 2026,
      "contributionType": "revolving"
    },
    "gateway": "internal",
    "date": "2026-01-05T00:00:00.000Z",
    "updatedAt": "2026-01-05T00:00:00.000Z"
  },
  {
    "seedKey": "transaction-contribution-member-group-02-0040-2026-02",
    "_id": "84aa013fdee13c31f6bffac4",
    "userId": "a9bad8af8ad2ff655f788f37",
    "reference": "GC-b053552258124657e9042abf",
    "amount": 45000,
    "type": "group_contribution",
    "status": "success",
    "description": "Group contribution - Golden Champions",
    "channel": "seed",
    "groupId": "f13266e9a87019f9d50f8c6c",
    "groupName": "Golden Champions",
    "metadata": {
      "contributionId": "b053552258124657e9042abf",
      "month": 2,
      "year": 2026,
      "contributionType": "revolving"
    },
    "gateway": "internal",
    "date": "2026-02-05T00:00:00.000Z",
    "updatedAt": "2026-02-05T00:00:00.000Z"
  },
  {
    "seedKey": "transaction-contribution-member-group-02-0041-2026-01",
    "_id": "e2e5a770c1a06484dd2eedef",
    "userId": "9835a14ffaf398426ae7be64",
    "reference": "GC-c8a336c228e4999a436e1be7",
    "amount": 100000,
    "type": "group_contribution",
    "status": "success",
    "description": "Group contribution - Golden Champions",
    "channel": "seed",
    "groupId": "f13266e9a87019f9d50f8c6c",
    "groupName": "Golden Champions",
    "metadata": {
      "contributionId": "c8a336c228e4999a436e1be7",
      "month": 1,
      "year": 2026,
      "contributionType": "revolving"
    },
    "gateway": "internal",
    "date": "2026-01-05T00:00:00.000Z",
    "updatedAt": "2026-01-05T00:00:00.000Z"
  },
  {
    "seedKey": "transaction-contribution-member-group-02-0041-2026-02",
    "_id": "570bd2ddd910df8d6368ac31",
    "userId": "9835a14ffaf398426ae7be64",
    "reference": "GC-64812d334382cc5b75627329",
    "amount": 50000,
    "type": "group_contribution",
    "status": "success",
    "description": "Group contribution - Golden Champions",
    "channel": "seed",
    "groupId": "f13266e9a87019f9d50f8c6c",
    "groupName": "Golden Champions",
    "metadata": {
      "contributionId": "64812d334382cc5b75627329",
      "month": 2,
      "year": 2026,
      "contributionType": "revolving"
    },
    "gateway": "internal",
    "date": "2026-02-05T00:00:00.000Z",
    "updatedAt": "2026-02-05T00:00:00.000Z"
  },
  {
    "seedKey": "transaction-contribution-member-group-02-0042-2026-01",
    "_id": "fc113ca465829dfd885f8537",
    "userId": "4ca5fd16575a4b50ce21693f",
    "reference": "GC-1753a2c77419f4ce3ed185cb",
    "amount": 100000,
    "type": "group_contribution",
    "status": "success",
    "description": "Group contribution - Golden Champions",
    "channel": "seed",
    "groupId": "f13266e9a87019f9d50f8c6c",
    "groupName": "Golden Champions",
    "metadata": {
      "contributionId": "1753a2c77419f4ce3ed185cb",
      "month": 1,
      "year": 2026,
      "contributionType": "revolving"
    },
    "gateway": "internal",
    "date": "2026-01-05T00:00:00.000Z",
    "updatedAt": "2026-01-05T00:00:00.000Z"
  },
  {
    "seedKey": "transaction-contribution-member-group-02-0042-2026-02",
    "_id": "81249dd654c95971b13c386d",
    "userId": "4ca5fd16575a4b50ce21693f",
    "reference": "GC-64431c37014c9c8cf92321fa",
    "amount": 50000,
    "type": "group_contribution",
    "status": "success",
    "description": "Group contribution - Golden Champions",
    "channel": "seed",
    "groupId": "f13266e9a87019f9d50f8c6c",
    "groupName": "Golden Champions",
    "metadata": {
      "contributionId": "64431c37014c9c8cf92321fa",
      "month": 2,
      "year": 2026,
      "contributionType": "revolving"
    },
    "gateway": "internal",
    "date": "2026-02-05T00:00:00.000Z",
    "updatedAt": "2026-02-05T00:00:00.000Z"
  },
  {
    "seedKey": "transaction-contribution-member-group-02-0043-2026-01",
    "_id": "1fe0053ad228bc05a4dbf3c7",
    "userId": "945c74c9a229b49a96d664e4",
    "reference": "GC-ae8d43f451099f01de2adba6",
    "amount": 100000,
    "type": "group_contribution",
    "status": "success",
    "description": "Group contribution - Golden Champions",
    "channel": "seed",
    "groupId": "f13266e9a87019f9d50f8c6c",
    "groupName": "Golden Champions",
    "metadata": {
      "contributionId": "ae8d43f451099f01de2adba6",
      "month": 1,
      "year": 2026,
      "contributionType": "revolving"
    },
    "gateway": "internal",
    "date": "2026-01-05T00:00:00.000Z",
    "updatedAt": "2026-01-05T00:00:00.000Z"
  },
  {
    "seedKey": "transaction-contribution-member-group-02-0043-2026-02",
    "_id": "3906648b140c8d50bc0e11f5",
    "userId": "945c74c9a229b49a96d664e4",
    "reference": "GC-81639b0b18e6fe92a19e1d09",
    "amount": 50000,
    "type": "group_contribution",
    "status": "success",
    "description": "Group contribution - Golden Champions",
    "channel": "seed",
    "groupId": "f13266e9a87019f9d50f8c6c",
    "groupName": "Golden Champions",
    "metadata": {
      "contributionId": "81639b0b18e6fe92a19e1d09",
      "month": 2,
      "year": 2026,
      "contributionType": "revolving"
    },
    "gateway": "internal",
    "date": "2026-02-05T00:00:00.000Z",
    "updatedAt": "2026-02-05T00:00:00.000Z"
  },
  {
    "seedKey": "transaction-contribution-member-group-02-0044-2026-01",
    "_id": "4f3d778af6244e035047eafe",
    "userId": "42f3b5f462c09e68f2e76275",
    "reference": "GC-4cd93ba0283d2a9e47d5eb22",
    "amount": 100000,
    "type": "group_contribution",
    "status": "success",
    "description": "Group contribution - Golden Champions",
    "channel": "seed",
    "groupId": "f13266e9a87019f9d50f8c6c",
    "groupName": "Golden Champions",
    "metadata": {
      "contributionId": "4cd93ba0283d2a9e47d5eb22",
      "month": 1,
      "year": 2026,
      "contributionType": "revolving"
    },
    "gateway": "internal",
    "date": "2026-01-05T00:00:00.000Z",
    "updatedAt": "2026-01-05T00:00:00.000Z"
  },
  {
    "seedKey": "transaction-contribution-member-group-02-0044-2026-02",
    "_id": "362db3adbc2ba63f26ab26aa",
    "userId": "42f3b5f462c09e68f2e76275",
    "reference": "GC-30635e038ab3371ec7128102",
    "amount": 50000,
    "type": "group_contribution",
    "status": "success",
    "description": "Group contribution - Golden Champions",
    "channel": "seed",
    "groupId": "f13266e9a87019f9d50f8c6c",
    "groupName": "Golden Champions",
    "metadata": {
      "contributionId": "30635e038ab3371ec7128102",
      "month": 2,
      "year": 2026,
      "contributionType": "revolving"
    },
    "gateway": "internal",
    "date": "2026-02-05T00:00:00.000Z",
    "updatedAt": "2026-02-05T00:00:00.000Z"
  },
  {
    "seedKey": "transaction-contribution-member-group-02-0045-2026-01",
    "_id": "b847cc769ab3669548e2d371",
    "userId": "0bbe32afb707bd56d31da340",
    "reference": "GC-f14ea617768dec835e758a6d",
    "amount": 100000,
    "type": "group_contribution",
    "status": "success",
    "description": "Group contribution - Golden Champions",
    "channel": "seed",
    "groupId": "f13266e9a87019f9d50f8c6c",
    "groupName": "Golden Champions",
    "metadata": {
      "contributionId": "f14ea617768dec835e758a6d",
      "month": 1,
      "year": 2026,
      "contributionType": "revolving"
    },
    "gateway": "internal",
    "date": "2026-01-05T00:00:00.000Z",
    "updatedAt": "2026-01-05T00:00:00.000Z"
  },
  {
    "seedKey": "transaction-contribution-member-group-02-0045-2026-02",
    "_id": "8bdccc65b451f1f6e6ee8293",
    "userId": "0bbe32afb707bd56d31da340",
    "reference": "GC-4a238f912ebeb81d1ff3941d",
    "amount": 50000,
    "type": "group_contribution",
    "status": "success",
    "description": "Group contribution - Golden Champions",
    "channel": "seed",
    "groupId": "f13266e9a87019f9d50f8c6c",
    "groupName": "Golden Champions",
    "metadata": {
      "contributionId": "4a238f912ebeb81d1ff3941d",
      "month": 2,
      "year": 2026,
      "contributionType": "revolving"
    },
    "gateway": "internal",
    "date": "2026-02-05T00:00:00.000Z",
    "updatedAt": "2026-02-05T00:00:00.000Z"
  },
  {
    "seedKey": "transaction-contribution-member-group-02-0046-2026-01",
    "_id": "64d5d5623b5cb6f27c7b136a",
    "userId": "323f404baf9aa1bfca01663d",
    "reference": "GC-3c11c5add56543982afad4d4",
    "amount": 100000,
    "type": "group_contribution",
    "status": "success",
    "description": "Group contribution - Golden Champions",
    "channel": "seed",
    "groupId": "f13266e9a87019f9d50f8c6c",
    "groupName": "Golden Champions",
    "metadata": {
      "contributionId": "3c11c5add56543982afad4d4",
      "month": 1,
      "year": 2026,
      "contributionType": "revolving"
    },
    "gateway": "internal",
    "date": "2026-01-05T00:00:00.000Z",
    "updatedAt": "2026-01-05T00:00:00.000Z"
  },
  {
    "seedKey": "transaction-contribution-member-group-02-0046-2026-02",
    "_id": "387e4ee5571b39bafdb61456",
    "userId": "323f404baf9aa1bfca01663d",
    "reference": "GC-e9b01fbcdb41a5d6a495ec46",
    "amount": 50000,
    "type": "group_contribution",
    "status": "success",
    "description": "Group contribution - Golden Champions",
    "channel": "seed",
    "groupId": "f13266e9a87019f9d50f8c6c",
    "groupName": "Golden Champions",
    "metadata": {
      "contributionId": "e9b01fbcdb41a5d6a495ec46",
      "month": 2,
      "year": 2026,
      "contributionType": "revolving"
    },
    "gateway": "internal",
    "date": "2026-02-05T00:00:00.000Z",
    "updatedAt": "2026-02-05T00:00:00.000Z"
  },
  {
    "seedKey": "transaction-contribution-member-group-02-0047-2026-01",
    "_id": "12a6dc61a12c859c62971310",
    "userId": "ff4e1a14bd7780373f9490fe",
    "reference": "GC-8632869392f2f50e54b2d52b",
    "amount": 120000,
    "type": "group_contribution",
    "status": "success",
    "description": "Group contribution - Golden Champions",
    "channel": "seed",
    "groupId": "f13266e9a87019f9d50f8c6c",
    "groupName": "Golden Champions",
    "metadata": {
      "contributionId": "8632869392f2f50e54b2d52b",
      "month": 1,
      "year": 2026,
      "contributionType": "revolving"
    },
    "gateway": "internal",
    "date": "2026-01-05T00:00:00.000Z",
    "updatedAt": "2026-01-05T00:00:00.000Z"
  },
  {
    "seedKey": "transaction-contribution-member-group-02-0047-2026-02",
    "_id": "a35bb5e527450ac625eb2480",
    "userId": "ff4e1a14bd7780373f9490fe",
    "reference": "GC-e39a044994104855d027a157",
    "amount": 60000,
    "type": "group_contribution",
    "status": "success",
    "description": "Group contribution - Golden Champions",
    "channel": "seed",
    "groupId": "f13266e9a87019f9d50f8c6c",
    "groupName": "Golden Champions",
    "metadata": {
      "contributionId": "e39a044994104855d027a157",
      "month": 2,
      "year": 2026,
      "contributionType": "revolving"
    },
    "gateway": "internal",
    "date": "2026-02-05T00:00:00.000Z",
    "updatedAt": "2026-02-05T00:00:00.000Z"
  },
  {
    "seedKey": "transaction-contribution-member-group-02-0048-2026-01",
    "_id": "f23484dc106e6dd7923d7545",
    "userId": "caccdd6f9f249fe025a4c09b",
    "reference": "GC-5d93382fec6fad02ee62e7aa",
    "amount": 120000,
    "type": "group_contribution",
    "status": "success",
    "description": "Group contribution - Golden Champions",
    "channel": "seed",
    "groupId": "f13266e9a87019f9d50f8c6c",
    "groupName": "Golden Champions",
    "metadata": {
      "contributionId": "5d93382fec6fad02ee62e7aa",
      "month": 1,
      "year": 2026,
      "contributionType": "revolving"
    },
    "gateway": "internal",
    "date": "2026-01-05T00:00:00.000Z",
    "updatedAt": "2026-01-05T00:00:00.000Z"
  },
  {
    "seedKey": "transaction-contribution-member-group-02-0048-2026-02",
    "_id": "e4d0405e3b24bd03786c253f",
    "userId": "caccdd6f9f249fe025a4c09b",
    "reference": "GC-7596f5d1c43d8454eb4e0efd",
    "amount": 60000,
    "type": "group_contribution",
    "status": "success",
    "description": "Group contribution - Golden Champions",
    "channel": "seed",
    "groupId": "f13266e9a87019f9d50f8c6c",
    "groupName": "Golden Champions",
    "metadata": {
      "contributionId": "7596f5d1c43d8454eb4e0efd",
      "month": 2,
      "year": 2026,
      "contributionType": "revolving"
    },
    "gateway": "internal",
    "date": "2026-02-05T00:00:00.000Z",
    "updatedAt": "2026-02-05T00:00:00.000Z"
  },
  {
    "seedKey": "transaction-contribution-member-group-02-0049-2026-01",
    "_id": "6a861739f742453f4d909b24",
    "userId": "8a47d60f496d68074fd09aa8",
    "reference": "GC-c9368c8e14670d13e88f1f3a",
    "amount": 140000,
    "type": "group_contribution",
    "status": "success",
    "description": "Group contribution - Golden Champions",
    "channel": "seed",
    "groupId": "f13266e9a87019f9d50f8c6c",
    "groupName": "Golden Champions",
    "metadata": {
      "contributionId": "c9368c8e14670d13e88f1f3a",
      "month": 1,
      "year": 2026,
      "contributionType": "revolving"
    },
    "gateway": "internal",
    "date": "2026-01-05T00:00:00.000Z",
    "updatedAt": "2026-01-05T00:00:00.000Z"
  },
  {
    "seedKey": "transaction-contribution-member-group-02-0049-2026-02",
    "_id": "f169b96bfc9c76f704cd9f83",
    "userId": "8a47d60f496d68074fd09aa8",
    "reference": "GC-ee0d4611aea4785c0d23e963",
    "amount": 70000,
    "type": "group_contribution",
    "status": "success",
    "description": "Group contribution - Golden Champions",
    "channel": "seed",
    "groupId": "f13266e9a87019f9d50f8c6c",
    "groupName": "Golden Champions",
    "metadata": {
      "contributionId": "ee0d4611aea4785c0d23e963",
      "month": 2,
      "year": 2026,
      "contributionType": "revolving"
    },
    "gateway": "internal",
    "date": "2026-02-05T00:00:00.000Z",
    "updatedAt": "2026-02-05T00:00:00.000Z"
  },
  {
    "seedKey": "transaction-contribution-member-group-02-0050-2026-01",
    "_id": "98218fe59ac8f81b2776fac7",
    "userId": "24d9cb78ccfc8f072c160b83",
    "reference": "GC-f6e4fb7864bf1a7e949455f5",
    "amount": 160000,
    "type": "group_contribution",
    "status": "success",
    "description": "Group contribution - Golden Champions",
    "channel": "seed",
    "groupId": "f13266e9a87019f9d50f8c6c",
    "groupName": "Golden Champions",
    "metadata": {
      "contributionId": "f6e4fb7864bf1a7e949455f5",
      "month": 1,
      "year": 2026,
      "contributionType": "revolving"
    },
    "gateway": "internal",
    "date": "2026-01-05T00:00:00.000Z",
    "updatedAt": "2026-01-05T00:00:00.000Z"
  },
  {
    "seedKey": "transaction-contribution-member-group-02-0050-2026-02",
    "_id": "265d56d05f17a2d6fc5c8e4f",
    "userId": "24d9cb78ccfc8f072c160b83",
    "reference": "GC-6b3dfe0ab91a1e10c4c06380",
    "amount": 80000,
    "type": "group_contribution",
    "status": "success",
    "description": "Group contribution - Golden Champions",
    "channel": "seed",
    "groupId": "f13266e9a87019f9d50f8c6c",
    "groupName": "Golden Champions",
    "metadata": {
      "contributionId": "6b3dfe0ab91a1e10c4c06380",
      "month": 2,
      "year": 2026,
      "contributionType": "revolving"
    },
    "gateway": "internal",
    "date": "2026-02-05T00:00:00.000Z",
    "updatedAt": "2026-02-05T00:00:00.000Z"
  },
  {
    "seedKey": "transaction-contribution-member-group-02-0051-2026-01",
    "_id": "fe2062e4995a353c6a972410",
    "userId": "d57eb1de527af1598b57de58",
    "reference": "GC-fa860c0371e1aa12ec48decb",
    "amount": 200000,
    "type": "group_contribution",
    "status": "success",
    "description": "Group contribution - Golden Champions",
    "channel": "seed",
    "groupId": "f13266e9a87019f9d50f8c6c",
    "groupName": "Golden Champions",
    "metadata": {
      "contributionId": "fa860c0371e1aa12ec48decb",
      "month": 1,
      "year": 2026,
      "contributionType": "revolving"
    },
    "gateway": "internal",
    "date": "2026-01-05T00:00:00.000Z",
    "updatedAt": "2026-01-05T00:00:00.000Z"
  },
  {
    "seedKey": "transaction-contribution-member-group-02-0051-2026-02",
    "_id": "327e6fe35b53cec7da267329",
    "userId": "d57eb1de527af1598b57de58",
    "reference": "GC-21608b33a9bc0ce873346694",
    "amount": 100000,
    "type": "group_contribution",
    "status": "success",
    "description": "Group contribution - Golden Champions",
    "channel": "seed",
    "groupId": "f13266e9a87019f9d50f8c6c",
    "groupName": "Golden Champions",
    "metadata": {
      "contributionId": "21608b33a9bc0ce873346694",
      "month": 2,
      "year": 2026,
      "contributionType": "revolving"
    },
    "gateway": "internal",
    "date": "2026-02-05T00:00:00.000Z",
    "updatedAt": "2026-02-05T00:00:00.000Z"
  },
  {
    "seedKey": "transaction-contribution-member-group-02-0052-2026-01",
    "_id": "43d1307cb0b40700cd3f25fe",
    "userId": "5e53e10fa01e9c1011725620",
    "reference": "GC-591b2b77a974d17dcd4edf81",
    "amount": 210000,
    "type": "group_contribution",
    "status": "success",
    "description": "Group contribution - Golden Champions",
    "channel": "seed",
    "groupId": "f13266e9a87019f9d50f8c6c",
    "groupName": "Golden Champions",
    "metadata": {
      "contributionId": "591b2b77a974d17dcd4edf81",
      "month": 1,
      "year": 2026,
      "contributionType": "revolving"
    },
    "gateway": "internal",
    "date": "2026-01-05T00:00:00.000Z",
    "updatedAt": "2026-01-05T00:00:00.000Z"
  },
  {
    "seedKey": "transaction-contribution-member-group-02-0052-2026-02",
    "_id": "d55134e41ca3f25962b6b5cb",
    "userId": "5e53e10fa01e9c1011725620",
    "reference": "GC-38c35efed42b929f405abccc",
    "amount": 105000,
    "type": "group_contribution",
    "status": "success",
    "description": "Group contribution - Golden Champions",
    "channel": "seed",
    "groupId": "f13266e9a87019f9d50f8c6c",
    "groupName": "Golden Champions",
    "metadata": {
      "contributionId": "38c35efed42b929f405abccc",
      "month": 2,
      "year": 2026,
      "contributionType": "revolving"
    },
    "gateway": "internal",
    "date": "2026-02-05T00:00:00.000Z",
    "updatedAt": "2026-02-05T00:00:00.000Z"
  },
  {
    "seedKey": "transaction-contribution-member-group-02-0053-2026-01",
    "_id": "8756f400b7c4ddc6e9c13113",
    "userId": "6dd6bc7b803d9b818a5a2962",
    "reference": "GC-6951e5a7332e90ec1e6f2978",
    "amount": 220000,
    "type": "group_contribution",
    "status": "success",
    "description": "Group contribution - Golden Champions",
    "channel": "seed",
    "groupId": "f13266e9a87019f9d50f8c6c",
    "groupName": "Golden Champions",
    "metadata": {
      "contributionId": "6951e5a7332e90ec1e6f2978",
      "month": 1,
      "year": 2026,
      "contributionType": "revolving"
    },
    "gateway": "internal",
    "date": "2026-01-05T00:00:00.000Z",
    "updatedAt": "2026-01-05T00:00:00.000Z"
  },
  {
    "seedKey": "transaction-contribution-member-group-02-0053-2026-02",
    "_id": "2d706cb42bd23a85ebf1adbe",
    "userId": "6dd6bc7b803d9b818a5a2962",
    "reference": "GC-2f749c7ed074f8884d12c2f2",
    "amount": 110000,
    "type": "group_contribution",
    "status": "success",
    "description": "Group contribution - Golden Champions",
    "channel": "seed",
    "groupId": "f13266e9a87019f9d50f8c6c",
    "groupName": "Golden Champions",
    "metadata": {
      "contributionId": "2f749c7ed074f8884d12c2f2",
      "month": 2,
      "year": 2026,
      "contributionType": "revolving"
    },
    "gateway": "internal",
    "date": "2026-02-05T00:00:00.000Z",
    "updatedAt": "2026-02-05T00:00:00.000Z"
  },
  {
    "seedKey": "transaction-contribution-member-group-02-0054-2026-01",
    "_id": "a9d5b2409ad0ae09b04651d2",
    "userId": "2024b93844e7c9bc27dc3a13",
    "reference": "GC-34dc22b0c548d62d6ef8f8e8",
    "amount": 350000,
    "type": "group_contribution",
    "status": "success",
    "description": "Group contribution - Golden Champions",
    "channel": "seed",
    "groupId": "f13266e9a87019f9d50f8c6c",
    "groupName": "Golden Champions",
    "metadata": {
      "contributionId": "34dc22b0c548d62d6ef8f8e8",
      "month": 1,
      "year": 2026,
      "contributionType": "revolving"
    },
    "gateway": "internal",
    "date": "2026-01-05T00:00:00.000Z",
    "updatedAt": "2026-01-05T00:00:00.000Z"
  },
  {
    "seedKey": "transaction-contribution-member-group-02-0054-2026-02",
    "_id": "6b5c0362904ecc4fa44d3b77",
    "userId": "2024b93844e7c9bc27dc3a13",
    "reference": "GC-06825668d8046f9d3456754e",
    "amount": 150000,
    "type": "group_contribution",
    "status": "success",
    "description": "Group contribution - Golden Champions",
    "channel": "seed",
    "groupId": "f13266e9a87019f9d50f8c6c",
    "groupName": "Golden Champions",
    "metadata": {
      "contributionId": "06825668d8046f9d3456754e",
      "month": 2,
      "year": 2026,
      "contributionType": "revolving"
    },
    "gateway": "internal",
    "date": "2026-02-05T00:00:00.000Z",
    "updatedAt": "2026-02-05T00:00:00.000Z"
  },
  {
    "seedKey": "transaction-contribution-member-group-02-0055-2026-01",
    "_id": "97f847727c5bfa1ffa8ad0f7",
    "userId": "84a32c3592bd3101427054f7",
    "reference": "GC-4f17d54e48e7e10a20b5f0e0",
    "amount": 400000,
    "type": "group_contribution",
    "status": "success",
    "description": "Group contribution - Golden Champions",
    "channel": "seed",
    "groupId": "f13266e9a87019f9d50f8c6c",
    "groupName": "Golden Champions",
    "metadata": {
      "contributionId": "4f17d54e48e7e10a20b5f0e0",
      "month": 1,
      "year": 2026,
      "contributionType": "revolving"
    },
    "gateway": "internal",
    "date": "2026-01-05T00:00:00.000Z",
    "updatedAt": "2026-01-05T00:00:00.000Z"
  },
  {
    "seedKey": "transaction-contribution-member-group-02-0055-2026-02",
    "_id": "b9c39894f4eb45c430b6429b",
    "userId": "84a32c3592bd3101427054f7",
    "reference": "GC-cc54830e8a227be300a13c4a",
    "amount": 200000,
    "type": "group_contribution",
    "status": "success",
    "description": "Group contribution - Golden Champions",
    "channel": "seed",
    "groupId": "f13266e9a87019f9d50f8c6c",
    "groupName": "Golden Champions",
    "metadata": {
      "contributionId": "cc54830e8a227be300a13c4a",
      "month": 2,
      "year": 2026,
      "contributionType": "revolving"
    },
    "gateway": "internal",
    "date": "2026-02-05T00:00:00.000Z",
    "updatedAt": "2026-02-05T00:00:00.000Z"
  },
  {
    "seedKey": "transaction-contribution-member-group-02-0056-2026-01",
    "_id": "fa448db9d72dcc1552fc8356",
    "userId": "1200dccc21f68645cc93ce8c",
    "reference": "GC-7fa933e77235c7ff3c80434d",
    "amount": 500000,
    "type": "group_contribution",
    "status": "success",
    "description": "Group contribution - Golden Champions",
    "channel": "seed",
    "groupId": "f13266e9a87019f9d50f8c6c",
    "groupName": "Golden Champions",
    "metadata": {
      "contributionId": "7fa933e77235c7ff3c80434d",
      "month": 1,
      "year": 2026,
      "contributionType": "revolving"
    },
    "gateway": "internal",
    "date": "2026-01-05T00:00:00.000Z",
    "updatedAt": "2026-01-05T00:00:00.000Z"
  },
  {
    "seedKey": "transaction-contribution-member-group-02-0056-2026-02",
    "_id": "3a44013902bb9d22285b581d",
    "userId": "1200dccc21f68645cc93ce8c",
    "reference": "GC-8c5abed6188f5faeba7e9dee",
    "amount": 250000,
    "type": "group_contribution",
    "status": "success",
    "description": "Group contribution - Golden Champions",
    "channel": "seed",
    "groupId": "f13266e9a87019f9d50f8c6c",
    "groupName": "Golden Champions",
    "metadata": {
      "contributionId": "8c5abed6188f5faeba7e9dee",
      "month": 2,
      "year": 2026,
      "contributionType": "revolving"
    },
    "gateway": "internal",
    "date": "2026-02-05T00:00:00.000Z",
    "updatedAt": "2026-02-05T00:00:00.000Z"
  },
  {
    "seedKey": "transaction-contribution-member-group-02-0057-2026-01",
    "_id": "925c50cc3f7460c2ac28b553",
    "userId": "b1b722fe889262f4258410c2",
    "reference": "GC-9d7fd082c7737993839e39ea",
    "amount": 600000,
    "type": "group_contribution",
    "status": "success",
    "description": "Group contribution - Golden Champions",
    "channel": "seed",
    "groupId": "f13266e9a87019f9d50f8c6c",
    "groupName": "Golden Champions",
    "metadata": {
      "contributionId": "9d7fd082c7737993839e39ea",
      "month": 1,
      "year": 2026,
      "contributionType": "revolving"
    },
    "gateway": "internal",
    "date": "2026-01-05T00:00:00.000Z",
    "updatedAt": "2026-01-05T00:00:00.000Z"
  },
  {
    "seedKey": "transaction-contribution-member-group-02-0057-2026-02",
    "_id": "26a361fbe7fd7fef6e5efcfd",
    "userId": "b1b722fe889262f4258410c2",
    "reference": "GC-5b2126265cb6fb87f9cd78de",
    "amount": 300000,
    "type": "group_contribution",
    "status": "success",
    "description": "Group contribution - Golden Champions",
    "channel": "seed",
    "groupId": "f13266e9a87019f9d50f8c6c",
    "groupName": "Golden Champions",
    "metadata": {
      "contributionId": "5b2126265cb6fb87f9cd78de",
      "month": 2,
      "year": 2026,
      "contributionType": "revolving"
    },
    "gateway": "internal",
    "date": "2026-02-05T00:00:00.000Z",
    "updatedAt": "2026-02-05T00:00:00.000Z"
  },
  {
    "seedKey": "transaction-contribution-member-group-02-0058-2026-01",
    "_id": "740dd565684e15f35f9b14c8",
    "userId": "743bda21fc1c63429bb1c395",
    "reference": "GC-f56488a5931c9a70f624f72a",
    "amount": 800000,
    "type": "group_contribution",
    "status": "success",
    "description": "Group contribution - Golden Champions",
    "channel": "seed",
    "groupId": "f13266e9a87019f9d50f8c6c",
    "groupName": "Golden Champions",
    "metadata": {
      "contributionId": "f56488a5931c9a70f624f72a",
      "month": 1,
      "year": 2026,
      "contributionType": "revolving"
    },
    "gateway": "internal",
    "date": "2026-01-05T00:00:00.000Z",
    "updatedAt": "2026-01-05T00:00:00.000Z"
  },
  {
    "seedKey": "transaction-contribution-member-group-02-0058-2026-02",
    "_id": "8cd7cc5e61aeffdea37cd556",
    "userId": "743bda21fc1c63429bb1c395",
    "reference": "GC-61d96231e93d8a05c55a1869",
    "amount": 400000,
    "type": "group_contribution",
    "status": "success",
    "description": "Group contribution - Golden Champions",
    "channel": "seed",
    "groupId": "f13266e9a87019f9d50f8c6c",
    "groupName": "Golden Champions",
    "metadata": {
      "contributionId": "61d96231e93d8a05c55a1869",
      "month": 2,
      "year": 2026,
      "contributionType": "revolving"
    },
    "gateway": "internal",
    "date": "2026-02-05T00:00:00.000Z",
    "updatedAt": "2026-02-05T00:00:00.000Z"
  }
]
